seekrai/__init__.py
seekrai/abstract/__init__.py
seekrai/abstract/api_requestor.py
seekrai/abstract/response_parsing.py
seekrai/client.py
seekrai/constants.py
seekrai/error.py
seekrai/filemanager.py
seekrai/resources/__init__.py
seekrai/resources/agents/__init__.py
seekrai/resources/agents/agent_inference.py
seekrai/resources/agents/agent_observability.py
seekrai/resources/agents/agents.py
seekrai/resources/agents/python_functions.py
seekrai/resources/agents/threads.py
seekrai/resources/alignment.py
seekrai/resources/chat/__init__.py
seekrai/resources/chat/completions.py
seekrai/resources/completions.py
seekrai/resources/deployments.py
seekrai/resources/embeddings.py
seekrai/resources/explainability.py
seekrai/resources/files.py
seekrai/resources/finetune.py
seekrai/resources/images.py
seekrai/resources/ingestion.py
seekrai/resources/models.py
seekrai/resources/projects.py
seekrai/resources/resource_base.py
seekrai/resources/vectordb.py
seekrai/seekrflow_response.py
seekrai/types/__init__.py
seekrai/types/abstract.py
seekrai/types/agents/__init__.py
seekrai/types/agents/agent.py
seekrai/types/agents/observability.py
seekrai/types/agents/python_functions.py
seekrai/types/agents/runs.py
seekrai/types/agents/threads.py
seekrai/types/agents/tools/__init__.py
seekrai/types/agents/tools/env_model_config.py
seekrai/types/agents/tools/schemas/__init__.py
seekrai/types/agents/tools/schemas/file_search.py
seekrai/types/agents/tools/schemas/file_search_env.py
seekrai/types/agents/tools/schemas/run_python.py
seekrai/types/agents/tools/schemas/run_python_env.py
seekrai/types/agents/tools/schemas/web_search.py
seekrai/types/agents/tools/schemas/web_search_env.py
seekrai/types/agents/tools/tool.py
seekrai/types/agents/tools/tool_types.py
seekrai/types/alignment.py
seekrai/types/chat_completions.py
seekrai/types/common.py
seekrai/types/completions.py
seekrai/types/deployments.py
seekrai/types/embeddings.py
seekrai/types/error.py
seekrai/types/explainability.py
seekrai-0.5.24.dist-info/LICENSE
seekrai-0.5.24.dist-info/METADATA
seekrai-0.5.24.dist-info/WHEEL
seekrai-0.5.24.dist-info/entry_points.txt
seekrai-0.5.24.dist-info/RECORD
