Metadata-Version: 2.1
Name: seekrai
Version: 0.5.24
Summary: Python client for SeekrAI
Home-page: https://www.seekr.com
License: Apache-2.0
Author: SeekrFlow
Author-email: support@seekr.com
Requires-Python: >=3.9,<4.0
Classifier: License :: OSI Approved :: Apache Software License
Classifier: Operating System :: POSIX :: Linux
Classifier: Programming Language :: Python :: 3
Classifier: Programming Language :: Python :: 3.9
Classifier: Programming Language :: Python :: 3.10
Classifier: Programming Language :: Python :: 3.11
Requires-Dist: click (>=8.1.7,<9.0.0)
Requires-Dist: eval-type-backport (>=0.1.3,<0.3.0)
Requires-Dist: filelock (>=3.13.1,<4.0.0)
Requires-Dist: httpx[http2] (>=0.27.0,<0.28.0)
Requires-Dist: numpy (>=1.23.5) ; python_version < "3.12"
Requires-Dist: numpy (>=1.26.0) ; python_version >= "3.12"
Requires-Dist: pillow (>=10.3.0,<11.0.0)
Requires-Dist: pyarrow (>=10.0.1)
Requires-Dist: pydantic (>=2.7,<3.0)
Requires-Dist: requests (>=2.31.0,<3.0.0)
Requires-Dist: tabulate (>=0.9.0,<0.10.0)
Requires-Dist: tqdm (>=4.66.2,<5.0.0)
Requires-Dist: typer (>=0.9,<0.13)
